rongyun_binding
