Metadata-Version: 1.0
Name: rongyun-binding
Version: 0.0.3
Summary: Integrate instant messaging services into your system
Home-page: https://github.com/ipconfiger/rongyun_binding
Author: Alexander.Li
Author-email: superpowerlee@gmail.com
License: GNU GENERAL PUBLIC LICENSE
Platform: UNKNOWN
